vitex_api_pkg/__init__.py
vitex_api_pkg/vitex_api.py
vitex_api-0.0.2.dist-info/LICENSE
vitex_api-0.0.2.dist-info/METADATA
vitex_api-0.0.2.dist-info/WHEEL
vitex_api-0.0.2.dist-info/top_level.txt
vitex_api-0.0.2.dist-info/RECORD
