Metadata-Version: 2.1
Name: vitex-api
Version: 0.0.2
Summary: Vitex API Python Package
Home-page: https://github.com/antonanufriev/vitex-api
Author: Anton Anufriev
Author-email: anufri3vant@gmail.com
License: UNKNOWN
Platform: UNKNOWN
Classifier: Programming Language :: Python :: 3
Classifier: License :: OSI Approved :: MIT License
Classifier: Operating System :: OS Independent
Requires-Python: >=3.7
